html2text/__init__.py
html2text/__main__.py
html2text/_typing.py
html2text/cli.py
html2text/config.py
html2text/elements.py
html2text/py.typed
html2text/utils.py
html2text2-1.1.1.dist-info/METADATA
html2text2-1.1.1.dist-info/WHEEL
html2text2-1.1.1.dist-info/entry_points.txt
html2text2-1.1.1.dist-info/licenses/COPYING
html2text2-1.1.1.dist-info/RECORD
