Metadata-Version: 2.1
Name: html2text2
Version: 1.1.1
Summary: Turn HTML into equivalent Markdown-structured text
Author-Email: Aaron Swartz <me@aaronsw.com>
Maintainer-Email: Alireza Savand <alireza.savand@gmail.com>
License:                     GNU GENERAL PUBLIC LICENSE
Requires-Python: >=3.8
